{
  "Name": "FHairMaterialPS",
  "EngineVersion": "5.1.1",
  "EngineSource": "Engine/Source/Runtime/Renderer/Private/HairStrands/HairStrandsVisibility.cpp:499 (FHairMaterialPS)",
  "LayoutHash": "0x00000000",
  "BindingFlags": "Shader",
  "ConstantBuffer": {
    "Name": "$Globals",
    "NameIndex": -1,
    "MatrixParameters": [],
    "VectorParameters": [
      {
        "Name": "MaterialPass_MacroGroupId",
        "NameIndex": -1,
        "Index": 0,
        "ArraySize": 0,
        "Type": "Float",
        "RowCount": 4,
        "ColumnCount": 1,
        "IsMatrix": false
      },
      {
        "Name": "MaterialPass_MaterialId",
        "NameIndex": -1,
        "Index": 16,
        "ArraySize": 0,
        "Type": "Float",
        "RowCount": 4,
        "ColumnCount": 1,
        "IsMatrix": false
      },
      {
        "Name": "MaterialPass_PrimitiveId",
        "NameIndex": -1,
        "Index": 32,
        "ArraySize": 0,
        "Type": "Float",
        "RowCount": 4,
        "ColumnCount": 1,
        "IsMatrix": false
      },
      {
        "Name": "MaterialPass_LightChannelMask",
        "NameIndex": -1,
        "Index": 48,
        "ArraySize": 0,
        "Type": "Float",
        "RowCount": 4,
        "ColumnCount": 1,
        "IsMatrix": false
      }
    ],
    "StructParameters": [],
    "Size": 64,
    "IsPartialCB": true
  },
  "Textures": [],
  "Samplers": [],
  "Buffers": [],
  "UAVs": [],
  "Resources": [],
  "Debug": {
    "ShaderTypeClass": "FHairMaterialPS",
    "ParentClass": "FMeshMaterialShader",
    "Note": "Source-derived name catalogue for the $Globals cbuffer + direct resource bindings of this FShader subclass. The ConstantBuffer offsets are SEQUENTIAL PLACEHOLDERS (16-byte stride in declaration order); the cook assigns real offsets per DXC packing of the HLSL source. Downstream loader must reconcile by name against the cooked binary."
  }
}
