{
  "Name": "LumenCardPass",
  "EngineVersion": "5.4.4",
  "EngineSource": "Engine/Source/Runtime/Renderer/Private/Lumen/LumenViewState.h",
  "LayoutHash": "0x09850A69",
  "BindingFlags": "Static",
  "ConstantBuffer": {
    "Name": "LumenCardPass",
    "NameIndex": -1,
    "MatrixParameters": [],
    "VectorParameters": [],
    "StructParameters": [],
    "Size": 128,
    "IsPartialCB": false
  },
  "Textures": [
    {
      "Name": "SceneTextures_SceneColorTexture",
      "NameIndex": -1,
      "Index": 0,
      "SamplerIndex": -1,
      "MultiSampled": false,
      "Dim": 2
    },
    {
      "Name": "SceneTextures_SceneDepthTexture",
      "NameIndex": -1,
      "Index": 1,
      "SamplerIndex": -1,
      "MultiSampled": false,
      "Dim": 2
    },
    {
      "Name": "SceneTextures_ScenePartialDepthTexture",
      "NameIndex": -1,
      "Index": 2,
      "SamplerIndex": -1,
      "MultiSampled": false,
      "Dim": 2
    },
    {
      "Name": "SceneTextures_GBufferATexture",
      "NameIndex": -1,
      "Index": 3,
      "SamplerIndex": -1,
      "MultiSampled": false,
      "Dim": 2
    },
    {
      "Name": "SceneTextures_GBufferBTexture",
      "NameIndex": -1,
      "Index": 4,
      "SamplerIndex": -1,
      "MultiSampled": false,
      "Dim": 2
    },
    {
      "Name": "SceneTextures_GBufferCTexture",
      "NameIndex": -1,
      "Index": 5,
      "SamplerIndex": -1,
      "MultiSampled": false,
      "Dim": 2
    },
    {
      "Name": "SceneTextures_GBufferDTexture",
      "NameIndex": -1,
      "Index": 6,
      "SamplerIndex": -1,
      "MultiSampled": false,
      "Dim": 2
    },
    {
      "Name": "SceneTextures_GBufferETexture",
      "NameIndex": -1,
      "Index": 7,
      "SamplerIndex": -1,
      "MultiSampled": false,
      "Dim": 2
    },
    {
      "Name": "SceneTextures_GBufferFTexture",
      "NameIndex": -1,
      "Index": 8,
      "SamplerIndex": -1,
      "MultiSampled": false,
      "Dim": 2
    },
    {
      "Name": "SceneTextures_GBufferVelocityTexture",
      "NameIndex": -1,
      "Index": 9,
      "SamplerIndex": -1,
      "MultiSampled": false,
      "Dim": 2
    },
    {
      "Name": "SceneTextures_ScreenSpaceAOTexture",
      "NameIndex": -1,
      "Index": 10,
      "SamplerIndex": -1,
      "MultiSampled": false,
      "Dim": 2
    },
    {
      "Name": "SceneTextures_CustomDepthTexture",
      "NameIndex": -1,
      "Index": 11,
      "SamplerIndex": -1,
      "MultiSampled": false,
      "Dim": 2
    },
    {
      "Name": "SceneTextures_CustomStencilTexture",
      "NameIndex": -1,
      "Index": 12,
      "SamplerIndex": -1,
      "MultiSampled": false,
      "Dim": 2
    }
  ],
  "Samplers": [
    {
      "Name": "SceneTextures_PointClampSampler",
      "Sampler": 13,
      "BindPoint": 13
    }
  ],
  "Buffers": [
    {
      "Name": "EyeAdaptationBuffer",
      "NameIndex": -1,
      "Index": 14,
      "ArraySize": 0
    }
  ],
  "UAVs": [],
  "Resources": [
    {
      "Index": 0,
      "Offset": 0,
      "Name": "SceneTextures_SceneColorTexture",
      "UbmtType": "UBMT_RDG_TEXTURE",
      "ShaderType": "Texture2D"
    },
    {
      "Index": 1,
      "Offset": 8,
      "Name": "SceneTextures_SceneDepthTexture",
      "UbmtType": "UBMT_RDG_TEXTURE",
      "ShaderType": "Texture2D"
    },
    {
      "Index": 2,
      "Offset": 16,
      "Name": "SceneTextures_ScenePartialDepthTexture",
      "UbmtType": "UBMT_RDG_TEXTURE",
      "ShaderType": "Texture2D"
    },
    {
      "Index": 3,
      "Offset": 24,
      "Name": "SceneTextures_GBufferATexture",
      "UbmtType": "UBMT_RDG_TEXTURE",
      "ShaderType": "Texture2D"
    },
    {
      "Index": 4,
      "Offset": 32,
      "Name": "SceneTextures_GBufferBTexture",
      "UbmtType": "UBMT_RDG_TEXTURE",
      "ShaderType": "Texture2D"
    },
    {
      "Index": 5,
      "Offset": 40,
      "Name": "SceneTextures_GBufferCTexture",
      "UbmtType": "UBMT_RDG_TEXTURE",
      "ShaderType": "Texture2D"
    },
    {
      "Index": 6,
      "Offset": 48,
      "Name": "SceneTextures_GBufferDTexture",
      "UbmtType": "UBMT_RDG_TEXTURE",
      "ShaderType": "Texture2D"
    },
    {
      "Index": 7,
      "Offset": 56,
      "Name": "SceneTextures_GBufferETexture",
      "UbmtType": "UBMT_RDG_TEXTURE",
      "ShaderType": "Texture2D"
    },
    {
      "Index": 8,
      "Offset": 64,
      "Name": "SceneTextures_GBufferFTexture",
      "UbmtType": "UBMT_RDG_TEXTURE",
      "ShaderType": "Texture2D"
    },
    {
      "Index": 9,
      "Offset": 72,
      "Name": "SceneTextures_GBufferVelocityTexture",
      "UbmtType": "UBMT_RDG_TEXTURE",
      "ShaderType": "Texture2D"
    },
    {
      "Index": 10,
      "Offset": 80,
      "Name": "SceneTextures_ScreenSpaceAOTexture",
      "UbmtType": "UBMT_RDG_TEXTURE",
      "ShaderType": "Texture2D"
    },
    {
      "Index": 11,
      "Offset": 88,
      "Name": "SceneTextures_CustomDepthTexture",
      "UbmtType": "UBMT_RDG_TEXTURE",
      "ShaderType": "Texture2D"
    },
    {
      "Index": 12,
      "Offset": 96,
      "Name": "SceneTextures_CustomStencilTexture",
      "UbmtType": "UBMT_RDG_TEXTURE_SRV",
      "ShaderType": "Texture2D<uint2>"
    },
    {
      "Index": 13,
      "Offset": 104,
      "Name": "SceneTextures_PointClampSampler",
      "UbmtType": "UBMT_SAMPLER",
      "ShaderType": "SamplerState"
    },
    {
      "Index": 14,
      "Offset": 112,
      "Name": "EyeAdaptationBuffer",
      "UbmtType": "UBMT_RDG_BUFFER_SRV",
      "ShaderType": "StructuredBuffer<float4>"
    }
  ]
}
