{
  "Name": "ShaderPrintUniform",
  "EngineVersion": "5.0.3",
  "EngineSource": "Engine/Source/Runtime/Renderer/Public/ShaderPrintParameters.h:32 (FUniformBufferParameters)",
  "LayoutHash": "0x00200100",
  "BindingFlags": "Shader",
  "ConstantBuffer": {
    "Name": "ShaderPrintUniform",
    "NameIndex": -1,
    "MatrixParameters": [],
    "VectorParameters": [
      {
        "Name": "FontSize",
        "NameIndex": -1,
        "Index": 0,
        "ArraySize": 0,
        "Type": "Float",
        "RowCount": 4,
        "ColumnCount": 1,
        "IsMatrix": false
      },
      {
        "Name": "Resolution",
        "NameIndex": -1,
        "Index": 16,
        "ArraySize": 0,
        "Type": "Int",
        "RowCount": 2,
        "ColumnCount": 1,
        "IsMatrix": false
      },
      {
        "Name": "MaxValueCount",
        "NameIndex": -1,
        "Index": 24,
        "ArraySize": 0,
        "Type": "Int",
        "RowCount": 1,
        "ColumnCount": 1,
        "IsMatrix": false
      },
      {
        "Name": "MaxSymbolCount",
        "NameIndex": -1,
        "Index": 28,
        "ArraySize": 0,
        "Type": "Int",
        "RowCount": 1,
        "ColumnCount": 1,
        "IsMatrix": false
      }
    ],
    "StructParameters": [],
    "Size": 32,
    "IsPartialCB": false
  },
  "Textures": [],
  "Samplers": [],
  "Buffers": [],
  "UAVs": [],
  "Resources": []
}
